{
  "$schema": "https://developer.microsoft.com/json-schemas/fabric/item/report/definition/visualContainer/2.4.0/schema.json",
  "name": "71f8af330ad2b9da2b22",
  "position": {
    "x": 85.239294710327457,
    "y": 32.6448362720403,
    "z": 0,
    "height": 262.97229219143577,
    "width": 394.45843828715363,
    "tabOrder": 0
  },
  "visual": {
    "visualType": "cardVisual",
    "query": {
      "queryState": {
        "Data": {
          "projections": [
            {
              "field": {
                "Measure": {
                  "Expression": {
                    "SourceRef": {
                      "Entity": "_Measures"
                    }
                  },
                  "Property": "1_Total_Quantity"
                }
              },
              "queryRef": "_Measures.1_Total_Quantity",
              "nativeQueryRef": "1_Total_Quantity"
            }
          ]
        }
      },
      "sortDefinition": {
        "sort": [
          {
            "field": {
              "Measure": {
                "Expression": {
                  "SourceRef": {
                    "Entity": "_Measures"
                  }
                },
                "Property": "1_Total_Quantity"
              }
            },
            "direction": "Descending"
          }
        ],
        "isDefaultSort": true
      }
    },
    "drillFilterOtherVisuals": true
  }
}